spectralexplain/__init__.py
spectralexplain/explainer.py
spectralexplain/interactions.py
spectralexplain/support_recovery.py
spectralexplain/utils.py
spectralexplain-0.0.3.dist-info/METADATA
spectralexplain-0.0.3.dist-info/WHEEL
spectralexplain-0.0.3.dist-info/licenses/LICENSE
spectralexplain-0.0.3.dist-info/RECORD
