Metadata-Version: 2.4
Name: spectralexplain
Version: 0.0.3
Summary: Spectral Explainer: Scalable Feature Interaction Attribution
Project-URL: Homepage, https://github.com/basics-lab/spectral-explain
Author-email: Justin Kang <justin_kang@berkeley.edu>, Landon Butler <landonb@berkeley.edu>, Yigit Efe Erginbas <erginbas@berkeley.edu>, Abhineet Agarwal <aa3797@berkeley.edu>
License-Expression: MIT
License-File: LICENSE
Classifier: License :: OSI Approved :: MIT License
Classifier: Operating System :: OS Independent
Classifier: Programming Language :: Python :: 3
Requires-Python: >=3.10
Requires-Dist: numpy>1.18
Requires-Dist: scikit-learn
Requires-Dist: sparse-transform
Requires-Dist: tqdm
Provides-Extra: dev
Requires-Dist: lime; extra == 'dev'
Requires-Dist: matplotlib; extra == 'dev'
Requires-Dist: openai; extra == 'dev'
Requires-Dist: openml; extra == 'dev'
Requires-Dist: pandas; extra == 'dev'
Requires-Dist: pillow; extra == 'dev'
Requires-Dist: pyrootutils; extra == 'dev'
Requires-Dist: shapiq; extra == 'dev'
Requires-Dist: torch>2.4; extra == 'dev'
Requires-Dist: transformers; extra == 'dev'
